{
    "faculty":[
        {
            "email":"DellingerBJ@gcc.edu",
            "firstName":"Brian",
            "lastName":"Dellinger",
            "middleInitial":"J",
            "title":"Dr.",
            "officeBuilding":"STEM",
            "officeNumber":"360A",
            "dept":"COMP"
        },
        {
            "email":"DickinsonBC@gcc.edu",
            "firstName":"Brian",
            "lastName":"Dickinson",
            "middleInitial":"C",
            "title":"Mr.",
            "officeBuilding":"STEM",
            "officeNumber":"340A",
            "dept":"COMP"
        },
        {
            "email":"HutchinsJO@gcc.edu",
            "firstName":"Jonathan ",
            "lastName":"Hutchins",
            "middleInitial":"C",
            "title":"Dr.",
            "officeBuilding":"STEM",
            "officeNumber":"340D",
            "dept":"COMP"
        },
        {
            "email":"JohnsonEJ@gcc.edu",
            "firstName":"Ethan",
            "lastName":"Johnson",
            "middleInitial":"J",
            "title":"Mr.",
            "officeBuilding":"STEM",
            "officeNumber":"360B",
            "dept":"COMP"
        },
        {
            "email":"WolfeBD@gcc.edu",
            "firstName":"Britton ",
            "lastName":"Wolfe",
            "middleInitial":"D",
            "title":"Dr.",
            "officeBuilding":"STEM",
            "officeNumber":"340B",
            "dept":"COMP"
        },
        {
            "email":"ZhangHD@gcc.edu",
            "firstName":"He “David”",
            "lastName":"Zhang",
            "middleInitial":"C",
            "title":"Dr.",
            "officeBuilding":"STEM",
            "officeNumber":"360D",
            "dept":"COMP"
        },
        {
            "email":"StauffDLD@gcc.edu",
            "firstName":"Devin",
            "lastName":"Stauff",
            "middleInitial":"L",
            "title":"Dr.",
            "officeBuilding":"PLC",
            "officeNumber":"220",
            "dept":"BIOL"
        },
        {
            "email":"AntoszewskiLM@gcc.edu",
            "firstName":"Lisa ",
            "lastName":"Antoszewski",
            "middleInitial":"",
            "title":"Dr.",
            "officeBuilding":"STEM",
            "officeNumber":"240A",
            "dept":"BIOL"
        },
        {
            "email":"CampagnoloER@gcc.edu",
            "firstName":"Enzo",
            "lastName":"Campagnolo",
            "middleInitial":"R",
            "title":"Dr.",
            "officeBuilding":"PLC",
            "officeNumber":"200",
            "dept":"BIOL"
        },
        {
            "email":"DudtJD@gcc.edu",
            "firstName":"Jan",
            "lastName":"Dudt",
            "middleInitial":"F",
            "title":"Dr.",
            "officeBuilding":"STEM",
            "officeNumber":"360C",
            "dept":"BIOL"
        },
        {
            "email":"FaroneTS@gcc.edu",
            "firstName":"Tracy",
            "lastName":"Farone",
            "middleInitial":"S",
            "title":"Dr.",
            "officeBuilding":"STEM",
            "officeNumber":"240B",
            "dept":"BIOL"
        },
        {
            "email":"JenkinsSP@gcc.edu",
            "firstName":"Stephen",
            "lastName":"Jenkins",
            "middleInitial":"P",
            "title":"Dr.",
            "officeBuilding":"STEM",
            "officeNumber":"260D",
            "dept":"BIOL"
        },
        {
            "email":"PazehoskiKO@gcc.edu",
            "firstName":"Kristina",
            "lastName":"Pazehoski",
            "middleInitial":"O",
            "title":"Dr.",
            "officeBuilding":"STEM",
            "officeNumber":"260E",
            "dept":"BIOL"
        },
        {
            "email":"WoodDM@gcc.edu",
            "firstName":"Darren ",
            "lastName":"Wood",
            "middleInitial":"M",
            "title":"Dr.",
            "officeBuilding":"PLC",
            "officeNumber":"222",
            "dept":"BIOL"
        },
        {
            "email":"YowlerBC@gcc.edu",
            "firstName":"Brian",
            "lastName":"Yowler",
            "middleInitial":"M",
            "title":"Dr.",
            "officeBuilding":"STEM",
            "officeNumber":"240C",
            "dept":"BIOL"
        },
        {
            "email":"AugspurgeJDr@gcc.edu",
            "firstName":"Joseph",
            "lastName":"Augspurger",
            "middleInitial":"D",
            "title":"Dr.",
            "officeBuilding":"STEM",
            "officeNumber":"160A",
            "dept":"CHEM"
        },
        {
            "email":"CramerSJ@gcc.edu",
            "firstName":"Susan",
            "lastName":"Cramer",
            "middleInitial":"J",
            "title":"Dr.",
            "officeBuilding":"STEM",
            "officeNumber":"240D",
            "dept":"CHEM"
        },
        {
            "email":"DiStasivf@gcc.edu",
            "firstName":"Vincent ",
            "lastName":"DiStasi",
            "middleInitial":"F",
            "title":"Dr.",
            "officeBuilding":"TLC",
            "officeNumber":"",
            "dept":"CHEM"
        },
        {
            "email":"FalcettaMF@gcc.edu",
            "firstName":"Michael ",
            "lastName":"Falcetta",
            "middleInitial":"F",
            "title":"Dr.",
            "officeBuilding":"PLS",
            "officeNumber":"218",
            "dept":"CHEM"
        },
        {
            "email":"FosterPW@gcc.edu",
            "firstName":"Peter",
            "lastName":"Foster",
            "middleInitial":"W",
            "title":"Dr.",
            "officeBuilding":"PLC",
            "officeNumber":"200",
            "dept":"CHEM"
        },
        {
            "email":"HomanTC@gcc.edu",
            "firstName":"Timothy",
            "lastName":"Homan",
            "middleInitial":"C",
            "title":"Dr.",
            "officeBuilding":"STEM",
            "officeNumber":"260B",
            "dept":"CHEM"
        },
        {
            "email":"KrileyCE@gcc.edu",
            "firstName":"Charles ",
            "lastName":"Kriley",
            "middleInitial":"E",
            "title":"Dr.",
            "officeBuilding":"STEM",
            "officeNumber":"260C",
            "dept":"CHEM"
        },
        {
            "email":"ShawKL@gcc.edu",
            "firstName":"Kevin",
            "lastName":"Shaw",
            "middleInitial":"L",
            "title":"Dr.",
            "officeBuilding":"STEM",
            "officeNumber":"340C",
            "dept":"CHEM"
        },
        {
            "email":"WongV@gcc.edu",
            "firstName":"Venney",
            "lastName":"Wong",
            "middleInitial":"",
            "title":"Dr.",
            "officeBuilding":"STEM",
            "officeNumber":"240E",
            "dept":"CHEM"
        },
        {
            "email":"BrooksBD@gcc.edu",
            "firstName":"James",
            "lastName":"Brooks",
            "middleInitial":"D",
            "title":"Dr.",
            "officeBuilding":"HOYT",
            "officeNumber":"212",
            "dept":"ELEE"
        },
        {
            "email":"BrightMW@gcc.edu",
            "firstName":"Myron “Mike”",
            "lastName":"Bright",
            "middleInitial":"W",
            "title":"Dr.",
            "officeBuilding":"HOYT",
            "officeNumber":"207B",
            "dept":"ELEE"
        },
        {
            "email":"ChristmanAM@gcc.edu",
            "firstName":"Alan",
            "lastName":"Christman",
            "middleInitial":"M",
            "title":"Dr.",
            "officeBuilding":"HOYT",
            "officeNumber":"109",
            "dept":"ELEE"
        },
        {
            "email":"HillPD@gcc.edu",
            "firstName":"Peter",
            "lastName":"Hill",
            "middleInitial":"D",
            "title":"Dr.",
            "officeBuilding":"HOYT",
            "officeNumber":"205A",
            "dept":"ELEE"
        },
        {
            "email":"RumbaughLK@gcc.edu",
            "firstName":"Luke",
            "lastName":"Rumbaugh",
            "middleInitial":"K",
            "title":"Dr.",
            "officeBuilding":"HOYT",
            "officeNumber":"105",
            "dept":"ELEE"
        },
        {
            "email":"PrinsPJ@gcc.edu",
            "firstName":"Philip",
            "lastName":"Prins",
            "middleInitial":"J",
            "title":"Dr.",
            "officeBuilding":"PLC",
            "officeNumber":"202",
            "dept":"EXER"
        },
        {
            "email":"AultDL@gcc.edu",
            "firstName":"Dana ",
            "lastName":"Ault",
            "middleInitial":"L",
            "title":"Dr.",
            "officeBuilding":"PLC",
            "officeNumber":"204",
            "dept":"EXER"
        },
        {
            "email":"BuxtonJD@gcc.edu",
            "firstName":"Jeffrey",
            "lastName":"Buxton",
            "middleInitial":"D",
            "title":"Dr.",
            "officeBuilding":"PLC",
            "officeNumber":"208",
            "dept":"EXER"
        },
        {
            "email":"GerhartHD@gcc.edu",
            "firstName":"Hayden",
            "lastName":"Gerhart",
            "middleInitial":"D",
            "title":"Dr.",
            "officeBuilding":"PLC",
            "officeNumber":"206",
            "dept":"EXER"
        },
        {
            "email":"JacksonMA@gcc.edu",
            "firstName":"Michael ",
            "lastName":"Jackson",
            "middleInitial":"A",
            "title":"Dr.",
            "officeBuilding":"SHAL",
            "officeNumber":"213E",
            "dept":"MATH"
        },
        {
            "email":"BancroftED@gcc.edu",
            "firstName":"Eric ",
            "lastName":"Bancroft",
            "middleInitial":"D",
            "title":"Dr.",
            "officeBuilding":"SHAL",
            "officeNumber":"213F",
            "dept":"MATH"
        },
        {
            "email":"BonomoKH@gcc.edu",
            "firstName":"Kelleen ",
            "lastName":"Bonomo",
            "middleInitial":"H",
            "title":"Dr.",
            "officeBuilding":"SHAL",
            "officeNumber":"217B",
            "dept":"MATH"
        },
        {
            "email":"DraiR@gcc.edu",
            "firstName":"Remi",
            "lastName":"Drai",
            "middleInitial":"",
            "title":"Dr.",
            "officeBuilding":"SHAL",
            "officeNumber":"213B",
            "dept":"MATH"
        },
        {
            "email":"FlandersST@gcc.edu",
            "firstName":"Steven",
            "lastName":"Flanders",
            "middleInitial":"T",
            "title":"Dr.",
            "officeBuilding":"SHAL",
            "officeNumber":"213G",
            "dept":"MATH"
        },
        {
            "email":"McIntyreDL@gcc.edu",
            "firstName":"Dale",
            "lastName":"McIntyre",
            "middleInitial":"L",
            "title":"Dr.",
            "officeBuilding":"SHAL",
            "officeNumber":"213C",
            "dept":"MATH"
        },
        {
            "email":"SmithEC@gcc.edu",
            "firstName":"Ethan  ",
            "lastName":"Smith",
            "middleInitial":"C",
            "title":"Dr.",
            "officeBuilding":"SHAL",
            "officeNumber":"213A",
            "dept":"MATH"
        },
        {
            "email":"ThompsonGL@gcc.edu",
            "firstName":"Gary ",
            "lastName":"Thompson",
            "middleInitial":"L",
            "title":"Dr.",
            "officeBuilding":"SHAL",
            "officeNumber":"217G",
            "dept":"MATH"
        },
        {
            "email":"ClaussMA@gcc.edu",
            "firstName":"Michelle",
            "lastName":"Clauss",
            "middleInitial":"A",
            "title":"Dr.",
            "officeBuilding":"HOYT",
            "officeNumber":"209",
            "dept":"MECE"
        },
        {
            "email":"DixonJM@gcc.edu",
            "firstName":"John",
            "lastName":"Dixon",
            "middleInitial":"M",
            "title":"Dr.",
            "officeBuilding":"HOYT",
            "officeNumber":"203",
            "dept":"MECE"
        },
        {
            "email":"AndersonEJ@gcc.edu",
            "firstName":"Erik",
            "lastName":"Anderson",
            "middleInitial":"J",
            "title":"Dr.",
            "officeBuilding":"HOYT",
            "officeNumber":"208",
            "dept":"MECE"
        },
        {
            "email":"BardyER@gcc.edu",
            "firstName":"Erik",
            "lastName":"Bardy",
            "middleInitial":"R",
            "title":"Dr.",
            "officeBuilding":"HOYT",
            "officeNumber":"213",
            "dept":"MECE"
        },
        {
            "email":"FairMC@gcc.edu",
            "firstName":"Mark",
            "lastName":"Fair",
            "middleInitial":"C",
            "title":"Dr.",
            "officeBuilding":"HOYT",
            "officeNumber":"108",
            "dept":"MECE"
        },
        {
            "email":"FairL@gcc.edu",
            "firstName":"Qiuyan ",
            "lastName":"Li",
            "middleInitial":"",
            "title":"Dr.",
            "officeBuilding":"HOYT",
            "officeNumber":"211",
            "dept":"MECE"
        },
        {
            "email":"RichardsGA@gcc.edu",
            "firstName":"George “Geo”",
            "lastName":"Richards",
            "middleInitial":"A",
            "title":"Dr.",
            "officeBuilding":"HOYT",
            "officeNumber":"110",
            "dept":"MECE"
        },
        {
            "email":"UlrichVW@gcc.edu",
            "firstName":"Vernon",
            "lastName":"Ulrich",
            "middleInitial":"W",
            "title":"Dr.",
            "officeBuilding":"HOYT",
            "officeNumber":"207A",
            "dept":"MECE"
        },
        {
            "email":"WolinskiJP@gcc.edu",
            "firstName":"Jeffrey",
            "lastName":"Wolinski",
            "middleInitial":"P",
            "title":"Dr.",
            "officeBuilding":"PLC",
            "officeNumber":"200",
            "dept":"PHYS"
        },
        {
            "email":"BrowerSC@gcc.edu",
            "firstName":"Shane ",
            "lastName":"Brower",
            "middleInitial":"C",
            "title":"Dr.",
            "officeBuilding":"PLC",
            "officeNumber":"210",
            "dept":"PHYS"
        },
        {
            "email":"ClemJL@gcc.edu",
            "firstName":"James",
            "lastName":"Clem",
            "middleInitial":"L",
            "title":"Dr.",
            "officeBuilding":"PLC",
            "officeNumber":"216",
            "dept":"PHYS"
        },
        {
            "email":"MarschGA@gcc.edu",
            "firstName":"Glenn",
            "lastName":"Marsch",
            "middleInitial":"A",
            "title":"Dr.",
            "officeBuilding":"PLC",
            "officeNumber":"214",
            "dept":"PHYS"
        },
        {
            "email":"WagnerDJ@gcc.edu",
            "firstName":"Doris “DJ”",
            "lastName":"Wagner",
            "middleInitial":"J",
            "title":"Dr.",
            "officeBuilding":"PLC",
            "officeNumber":"212",
            "dept":"PHYS"
        }
    ]
}